deepproto/proto/common/v1/common_pb2.py
deepproto/proto/poll/v1/poll_pb2.py
deepproto/proto/poll/v1/poll_pb2_grpc.py
deepproto/proto/resource/v1/resource_pb2.py
deepproto/proto/tracepoint/v1/tracepoint_pb2.py
deepproto/proto/tracepoint/v1/tracepoint_pb2_grpc.py
deep_proto-1.0.5.dist-info/METADATA
deep_proto-1.0.5.dist-info/WHEEL
deep_proto-1.0.5.dist-info/RECORD
