Metadata-Version: 2.1
Name: deep-proto
Version: 1.0.5
Summary: DEEP Python Protobuf
Author-email: Intergral GmbH <support@intergral.com>, Ben Donnelly <b.w.donnelly1@gmail.com>
License-Expression: AGPL-3.0-only
Classifier: Development Status :: 4 - Beta
Classifier: Intended Audience :: Developers
Classifier: License :: OSI Approved :: GNU Affero General Public License v3
Classifier: Programming Language :: Python
Classifier: Programming Language :: Python :: 3
Classifier: Programming Language :: Python :: 3.7
Classifier: Programming Language :: Python :: 3.8
Classifier: Programming Language :: Python :: 3.9
Classifier: Programming Language :: Python :: 3.10
Classifier: Programming Language :: Python :: 3.11
Classifier: Typing :: Typed
Requires-Python: >3.7
